{
  "width": 8,
  "height": 8,
  "palette": [
    "#3C78DC",
    "#E65050",
    "#50BE78",
    "#E6C846"
  ],
  "walls": [
    [
      4,
      7
    ]
  ],
  "blocks": [
    {
      "pos": [
        3,
        7
      ],
      "color": 0
    },
    {
      "pos": [
        7,
        0
      ],
      "color": 1
    }
  ],
  "holes": [
    {
      "pos": [
        2,
        0
      ],
      "color": 1
    },
    {
      "pos": [
        3,
        0
      ],
      "color": 0
    }
  ],
  "bouncers": [],
  "difficulty": 3,
  "difficulty_label": "challenging"
}